[
  {
    "step": 0,
    "cards": [
      {
        "id": 1,
        "preTitle": "רגע לפני שמתחילים בהזמנה...",
        "title": "ברוכים הבאים ללומדת עולמות המידע!",
        "message": [
          "אל דאגה, לא נפריע לכם לבחור בין פיצה, סושי או המבורגר. אנחנו פשוט נצטרף אליכם למאחורי הקלעים של ההזמנה.",
          "בלי מילים מסובכות – רק סיטואציה מוכרת שמסתירה עולם שלם של מידע.",
          "אז מה נשאר? לבחור מסעדה ולהתחיל לגלות."
        ],
        "input": true,
        "buttonTask": {
          "src" : "././media/buttons/delivery-man.png",
          "msg" : "יאללה נזמין!"
        }
      }
    ]
  },
  {
    "step": 1,
    "cards": [
      {
        "id": 1,
        "message": [
          "כאן תתחילו כמו כל לקוח – עם רשימת מסעדות.", 
          "אבל הפעם תראו איך מאחורי כל קליק מסתתרים נתונים, מידע וידע"
        ],
        "buttonNext": true
      },
            {
        "id": 2,
        "message": [
          "גללו למטה ובחרו מסעדה שמעניינת אתכם. ", 
          "תוך כדי נבין מה הנתונים שמרכיבים את התצוגה הזאת"
        ],
        "buttonTask": {
          "src" : "././media/buttons/click.png",
          "msg" : "יאללה נבחר!"
        },
        "buttonBack": true
      }
    ]
  },
  {
   "step": 2,
   "cards": [
      {
        "id": 1,
        "message": [
          "לפני שתראו את עמוד המסעדה, נסתכל על הנתונים שמרכיבים אותה"
        ],
        "buttonNext": true
      },
      { 
        "id": 2,
        "message": [
          "אלו <strong class='text-[#48cae4]'>נתונים</strong> - ערכים גולמיים (לא מעובדים) שלא מקושרים בהכרח זה לזה"
        ],
        "table": true,
        "buttonBack": true,
        "buttonNext": true
      },
      { 
        "id": 3,
        "message": [
          "ככה נראים הנתונים הגולמיים:",
          "רשימות של מסעדות, מחירים, זמני משלוח – כל אלו הם נתונים גולמיים.",
          "הם מוצגים כאן בלי עיבוד, ובלי הקשר – פשוט כמו שהם, מאחורי הקלעים."
        ],
         "buttonTask": {
          "src" : "././media/buttons/visible.png",
          "msg" : "הצג כתצוגת אפליקציה"
        },
        "buttonBack": true
      }
    ]
  },
    {
   "step": 3,
   "cards": [
      {
        "id": 1,
        "title": "אחרי העיבוד – הנתונים הופכים למידע",
       "message": [
          "הנתונים שסודרו והוצגו בצורה ברורה – הופכים עכשיו למשהו שאנחנו באמת יכולים להשתמש בו.",
          "כאשר מקשרים בין נתונים, אפשר להבין מהם משהו! נוצר <strong class='text-[#48cae4]'>מידע</strong>",
          "במקום טבלה יבשה – אנחנו רואים מנות עם תמונות, דירוגים, תיאורים, תגיות (כמו 'פופולרי' או 'צמחוני') ואפשרויות סינון.",
          "ככה בדיוק נראה <strong class='text-[#48cae4]'>מידע</strong>: משהו שמאפשר לנו להבין, להשוות בין אפשרויות, ולקבל החלטה."
        ],
        "buttonTask": {
          "src" : "././media/buttons/click.png",
          "msg" : "יאללה נמשיך!"
        }
      }
    ]
  },
   {
   "step": 4,
   "cards": [
      {
        "id": 1,
        "delay": 3000,
        "message": [
          "איך ההמלצה הזאת נוצרה? זה לא סתם ניחוש...",
          "בחרו את המסעדה שתרצו להזמין ממנה, ונלמד כיצד ההמלצה מתגבשת"
        ],
        "buttonNext": true
      },
      {
        "id": 2,
        "message": [
        "אז מאיפה מזמינים?"
        ],
         "buttonOptions": [{
          "id" : "selfChoice",
          "src" : "././media/buttons/think-different.png",
          "msg" : "המסעדה שבחרתי מקודם"
         },
        {
          "id" : "recommendation",
          "src" : "././media/buttons/recommendation.png",
          "msg" : "יאללה ננסה את ההמלצה"
         }]
      }
    ]
  },
  {
    "step" : 5,
     "cards": [
      {
        "id": 1,
        "messageOptions": [
         {
            "recommendation": [
              "מעולה! הבחירה הזאת התבססה על ידע שהמערכת פיתחה במיוחד עבורך.",
              "במהלך הזמן נאספו <strong class='text-[#48cae4]'>נתונים</strong> שקשורים להרגלי ההזמנה שלך: מתי יש הזמנות, מה נבחר, מה דורג גבוה, ואפילו אילו מנות נשמרו למועדפים."
            ]
          },
          {
            "selfChoice": [
              "מצוין! הפעם זו הייתה בחירה אישית, שמתבססת על <strong class='text-[#48cae4]'>ידע</strong> שצברת עם הזמן.",
              "המערכת ביססה את ההמלצות שלה על דפוסי ההתנהגות שלך – אבל עכשיו אתה זה שהובלת את הבחירה.",
              "אבל לפי מה בחרת? איך מקבלים החלטה?"
            ]
          }
        ],
        "buttonNext": true
      },
      {
        "id": 2,
        "messageOptions": [
        {
          "recommendation": [
            "המערכת ארגנה את כל זה ל<strong class='text-[#48cae4]'>מידע</strong> – למשל: 'יש העדפה לאוכל איטלקי בשעות הערב', או 'מנות חריפות כמעט לא נבחרות'.",
            "ה<strong class='text-[#48cae4]'>מידע</strong> הזה הפך ל<strong class='text-[#48cae4]'>ידע</strong> מותאם אישית, שאִפשר לה להציע את ההמלצה שקיבלת עכשיו.",
            "בדיוק כמו שבני אדם עושים מתוך ניסיון, גם מערכת יכולה ללמוד ולכוון."
          ]
        },
        {
          "selfChoice": [
            "הבחירה שלך לא עמדה בפני עצמה – היא מבוססת על <strong class='text-[#48cae4]'>ידע</strong> אישי שהצטבר לאורך זמן.",
            "מכל הבחירות הקודמות נבנו <strong class='text-[#48cae4]'>נתונים</strong> שהפכו ל<strong class='text-[#48cae4]'>מידע</strong> – ממש כמו שהזיכרון שלך עובד.",
            "הדרך שבה אנו לומדים – מתוך ניסיון – דומה לדרך שבה נוצר <strong class='text-[#48cae4]'>ידע</strong> גם אצל מערכת ממוחשבת."
          ]
        }
      ],
         "buttonTask": {
          "src" : "././media/buttons/order.png",
          "msg" : "יאללה נזמין אוכל!"
        },
        "buttonBack" : true
      }
    ]
  },
  {
    "step" : 6,
    "cards": [
      {
        "id": 1,
        "message": [
        "כשאתם פותחים מנה באפליקציה, אתם רואים המון פרטים: שם, מחיר, תוספות, הערות ועוד.",
        "אבל לא כל המידע מוצג באותו אופן. בואו נבין את ההבדל בין <strong class='text-[#48cae4]'>נתונים מובנים</strong> ל־<strong class='text-[#48cae4]'>נתונים לא מובנים</strong>."
      ],
      "buttonNext" : true
      },
      {
        "id": 2,
        "message":[
          "לחצו על חלקים שונים במסך כדי ללמוד על נתונים מובנים ולא מובנים",
          "שימו לב שבשלב זה של הלומדה, לא מאופשר למלא שדות בנוגע להזמנה"
        ],
      "buttonBack" : true,
      "buttonTask" : {
        "src" : "././media/buttons/click.png",
        "msg" : "יאללה נלחץ!"
      }
      }
    ]
  },
  {
   "step": 7,
   "cards": [
      {
        "id": 1,
        "messageTable": [
        {
          "title": "נתון מובנה",
          "message": ["מאורגן בטבלאות לפי שדות קבועים (כמו גיל, שם, תאריך).", "קל לעיבוד בעזרת כלים סטנדרטיים."]
        },
        {
          "title": "נתון לא מובנה",
          "message": ["חסר מבנה קבוע – כולל טקסטים, תמונות, וידאו ומיילים.", "דורש עיבוד מתקדם או ניתוח תמונה."]
        }
        ],
        "buttonNext": true
      },
      {
        "id": 2,
        "title": "ההבדל העיקרי",
        "message": [
          "<strong class='text-[#48cae4]'>נתון מובנה</strong> = עיבוד פשוט ומהיר",
          "<strong class='text-[#48cae4]'>נתון לא מובנה</strong> = עיבוד מורכב ומבוסס טכנולוגיות מתקדמות"
        ],
        "buttonNext": true,
        "buttonBack": true
      },
      {
        "id": 3,
        "message": ["עכשיו זה הזמן למלא את השינויים והתוספות שלך, ולהוסיף להזמנה!"],
        "buttonTask": {
          "src" : "././media/buttons/edit.png",
          "msg" : "יאללה נמלא ונוסיף!"
        }
      }
    ]
  },
  {
    "step": 8,
    "cards": [
      {
        "id": 1,
        "title": "אז איך המידע הזה נשמר?",
        "message": [
          "כל פרט שבחרת – המנה, הגודל, התוספות – נכנס בצורה מסודרת לתוך טבלה במערכת.",
          "כל שורה בטבלה מייצגת הזמנה או פריט, וכל עמודה מכילה פרט מסוים כמו שם המנה, המחיר וכו'.",
          "זו הדרך של מערכות לזכור דברים – באמצעות <strong class='text-[#48cae4]'>בסיס נתונים</strong>.",
          "<br>בואו נראה איך זה קורה מאחורי הקלעים..."
        ],
        "buttonNext": true
      },
      {
        "id": 2,
        "title": "שומרים את הנתונים...",
        "buttonNext": true,
        "buttonBack": true
      },
       {
        "id": 3,
        "title": "מה זה בסיס נתונים?",
        "message": [
          "<strong class='text-[#48cae4]'>בסיס נתונים הוא מאגר דיגיטלי שבו נשמר כל המידע של המערכת בצורה מסודרת – בדומה לאוסף של טבלאות.</strong>",
          "כל טבלה שומרת מידע מסוג מסוים: טבלת הזמנות, טבלת מסעדות, טבלת משתמשים, ועוד."
        ],
        "buttonNext": true,
        "buttonBack": true
      },
      {
        "id": 4,
        "message": [
          "במערכת ההזמנות של Flowt, כל פעולה (כמו ביצוע הזמנה) מתועדת ונשמרת בבסיס הנתונים, כדי לאפשר:",
          "• שליפה של מידע רלוונטי – למשל: מה הזמנת בעבר<br> • מעקב מדויק אחר סטטוס המשלוח<br> • הפעלה של שירותים חכמים – כמו המלצות מותאמות אישית",
          "בזכות זה, כל הזמנה נשמרת באופן מסודר, מאובטח ונגיש – גם עבורך כלקוח, וגם עבור המסעדה."
        ],
        "buttonBack": true,
        "buttonTask": {
          "src" : "././media/buttons/finish-order.png",
          "msg" : "יאללה נסיים את ההזמנה!"
        }
      }
    ]
  },
  {
    "step": 9,
    "cards": [
      {
        "id": 1,
        "delay": 3000,
        "title": "ברוכים הבאים למסך היסטוריית ההזמנות!",
        "message": [
          "איך בעצם ההזמנה שלכם הגיעה לכאן?",
          "ברגע שלחצתם 'סיום הזמנה' המערכת שמרה את כל פרטי ההזמנה בבסיס הנתונים.",
          "הפרטים האלה נשמרו בטבלה מיוחדת שנקראת Orders – טבלת ההזמנות.",
          "בואו נראה את זה מאחורי הקלעים!"
        ],
        "buttonNext": true
      },
      {
      "id": 2,
      "title": "Orders – טבלת ההזמנות",
      "ordersTable": true,
      "buttonNext": true,
      "buttonBack": true
      },
      {
      "id": 3,
      "title": "אז איך רק המידע הרלוונטי לכם מוצג?",
      "message": [
        "באמצעות <strong class='text-[#48cae4]'>אחזור מידע</strong>!",
        "אחזור הוא תהליך מציאת חומר רלוונטי מתוך אוסף גדול של נתונים",
        "המערכת מבצעת פעולה שנקראת '<strong class='text-[#48cae4]'>שליפה</strong>' – כלומר מחפשת בטבלה רק את ההזמנות שלכם.",
        "ואז מציגה אותן כאן – במסך היסטוריית ההזמנות.",
        "רק ההזמנות שלכם – לא של כולם 😉"
      ],
      "buttonNext": true,
      "buttonBack": true
    },
    {
    "id": 4,
    "title": "איך ההזמנה מופיעה למעלה – ואיך זה בכלל אפשרי?",
    "message": [
        "ההזמנות במסך הזה מגיעות מטבלה מסודרת בבסיס הנתונים – עם שדות כמו תאריך, שם מסעדה, מחיר וסטטוס.",
        "אלה <strong class='text-[#48cae4]'>נתונים מובנים</strong> – כאלה שכבר דיברנו עליהם קודם",
        "המערכת משתמשת בהם כדי למיין את ההזמנות (מהחדשה לישנה), לסנן לפי סטטוס, ולהציג פעולות כמו 'הזמן שוב'."
      ],
      "buttonNext": true,
      "buttonBack": true
    },
    {
    "id": 5,
    "title": "נסו זאת בעצמכם!",
    "message": [
      "המערכת יודעת לשלוף מידע מכל ההזמנות שלכם – אבל מה קורה כשאנחנו רוצים מידע ממוקד יותר?",
      "איך תעשו את זה? פשוט השתמשו במסנן למעלה!",
      "זה בדיוק מה שנקרא <strong class='text-[#48cae4]'>אחזור ממוקד</strong> – שליפה של מידע רלוונטי מתוך הרבה נתונים.",
      "יאללה ננסה? בחרו לפי העדפותיכם האישיות!"
    ],
    "buttonBack": true,
    "buttonTask": {
      "src": "././media/buttons/filter.png",
      "msg": "פתח מסנן"
    }
    }
    ]
  },
  {
    "step": 10,
    "cards": [
      {
        "id": 1,
        "delay": 2500,
        "title": "מה קורה מאחורי הקלעים?",
        "message": [
          "כשבחרתם מסנן – למשל סוג אוכל 'איטלקי' – המערכת לא סתם מציגה את זה מיד.",
          "היא בעצם שואלת את טבלת ההזמנות שאלה: <strong class='text-[#48cae4]'>מי כאן אוכל איטלקי?</strong>",
          "השאלה הזו נקראת <strong class='text-[#48cae4]'>שאילתה</strong>.",
          "המערכת רצה על כל ההזמנות, מחפשת את אלו שעונות לתנאים – ומחזירה רק אותן."
        ],
        "buttonNext": true
      },
      {
      "id": 2,
      "title": "הנה השאילתה שנעשתה עכשיו כשסיננת",
      "dynamicSql": true,
       "message": [
        "זו <strong class='text-[#48cae4]'>שאילתת SQL</strong> – שפה שהמערכת משתמשת בה כדי לחפש מידע בטבלה.",
        "המערכת בונה את השאילתה הזו <strong>אוטומטית</strong> לפי מה שבחרתם במסננים.",
        "בדיוק כמו שאמרתם:"
      ],
      "buttonBack": true,
      "buttonNext": true
     },
      {
    "id": 3,
    "title": "אבל למה צריך בכלל שאילתה?",
    "message": [
      "תארו לכם שהיו לנו מאות הזמנות, ואנחנו רוצים למצוא רק את מי שאוכל איטלקי עם דירוג 4 ומעלה.",
      "בלי שאילתה – היינו צריכים לבדוק ידנית כל הזמנה…",
      "<strong class='text-[#48cae4]'>השאילתה חוסכת לנו את זה!</strong>",
      "היא מחפשת בשבילנו <em>רק</em> את מה שעונה על התנאים – מהר, אוטומטית ובדיוק מירבי."
    ],
    "buttonBack": true,
    "buttonNext": true
    },
    {
      "id": 4,
      "title": "הסקת מסקנות באמצעות שאילתות",
      "message": [
        "עד עכשיו חיפשנו רשומות – למשל: <strong>איפה יש אוכל איטלקי?</strong>",
        "אבל לפעמים אנחנו רוצים להבין <strong>מגמות</strong> ולא פרטים:",
        "<ul class='list-disc pr-4'><li>מה אני מזמין הכי הרבה?</li><li>מתי אני נוטה להזמין – בצהריים או בערב?</li><li>האם אני מזמין יותר בקיץ או בחורף?</li></ul>",
        "כדי לענות על שאלות כאלה, אנחנו לא מחפשים שורה אחת בטבלה – אלא משתמשים בשאילתות <strong>שמסכמות מידע</strong>."
      ],
      "buttonBack": true,
      "buttonNext": true
    },
    {
      "id": 5,
      "message": [
         "זוכרים שבתחילת הלומדה הייתה לכם המלצה למסעדה?",
        "עכשיו, נראה את זה קורה – באמצעות <strong>גרפים ותובנות</strong> מהנתונים האישיים שלכם!"
      ],
      "buttonTask": {
        "src": "././media/buttons/insight.png",
        "msg": "יאללה, לגרפים!"
      },
      "buttonBack": true
    }
    ]
  },
  {
  "step": 11,
  "cards": [
      {
        "id": 1,
        "delay": 2500,
        "title": "איך המערכת יודעת להמליץ על קפה איטליה?",
        "message": [
          "כדי להמליץ לך על מסעדה, המערכת לא מחפשת פשוט מה שמתאים עכשיו – אלא מנסה להבין את ההרגלים שלך לאורך זמן.",
          "למשל: איזה סוג אוכל אתה הכי אוהב? ממי אתה מזמין שוב ושוב? מה דירגת הכי גבוה?",
          "כאן נכנס לתמונה <strong class='text-[#48cae4]'>תהליך מיצוי מידע</strong> – שבו מריצים שאילתות על הרבה נתונים כדי להסיק <strong>מסקנות</strong>."
        ],
        "buttonNext": true
      },
      {
        "id": 2,
        "title": "מנתחים את ההיסטוריה שלך",
        "message": [
          "המערכת בודקת את כל ההזמנות שביצעת – לאורך זמן.",
          "כדי להבין אילו סוגי אוכל אתה מזמין הכי הרבה, מריצים שאילתה כמו:",
          "<div class='bg-gray-900 text-green-400 p-4 rounded-lg font-mono text-sm text-left whitespace-pre-wrap break-words leading-relaxed'>SELECT type, COUNT(*) FROM Orders GROUP BY type</div>",
          "מה שמתקבל בעמוד הבא"
        ],
       
        "buttonNext": true,
        "buttonBack": true
      },
      { 
         "id": 3,
         "chart": {
          "type": "bar",
          "title": "עמודות סוגי האוכל שאתה מזמין",
          "xField": "סוג",
          "yField": "מספר הזמנות",
          "dataFrom": "orderHistoryGroupedByType"
        },
        "buttonNext": true,
        "buttonBack": true
      },
      {
        "id": 4,
        "title": "העדפות לאורך זמן",
        "message": [
          "אפשר גם לראות אם יש שינוי בהרגלים לאורך זמן – למשל, האם בתקופות מסוימות אתה מזמין אחרת?",
          "זו דוגמה לשאילתה נוספת:",
          "<div class='bg-gray-900 text-green-400 p-4 rounded-lg font-mono text-sm text-left whitespace-pre-wrap break-words leading-relaxed'>SELECT MONTH(orderDateTime) as month, COUNT(*) FROM Orders GROUP BY month</div>",
          "הגרף יופיע בכרטיסיה הבאה"
        ],
        
        "buttonNext": true,
        "buttonBack": true
      },
      {
        "id": 5,
        "chart": {
          "type": "line",
          "title": "כמות ההזמנות לפי חודשים",
          "xField": "חודש",
          "yField": "מספר הזמנות",
          "dataFrom": "orderHistoryGroupedByMonth"
        },
        "buttonNext": true,
        "buttonBack": true
      },
      {
        "id": 6,
        "title": "כך נבנית ההמלצה שלך",
        "message": [
          "אחרי ניתוח של הנתונים, מתברר שאתה הכי אוהב אוכל <strong>איטלקי</strong>, ומסעדה שקיבלה ממך דירוג גבוה במיוחד היא <strong>קפה איטליה</strong>.",
          "אז המערכת ממליצה לך להזמין דווקא ממנה 😋",
          "וזה כל הקסם של <strong class='text-[#48cae4]'>מיצוי מידע</strong>: להשתמש בשאלות חכמות כדי להגיע לתשובות שממש רלוונטיות עבורך."
        ],
        "buttonBack": true,
        "buttonTask": {
          "src": "././media/buttons/knowledge.png",
          "msg": "הבנתי מגניב"
        }
      }
    ]
  },
  {
    "step": 12,
    "cards": [
      {
        "id": 1,
         "delay": 2500,
        "title": "שמעתם פעם על מערכת <img src='public/media/LOGO-FLOW.png'/>?",
        "message": [
          "הסברים על פלואו"
        ]
      }
    ]
  }

]

